[
  {
    "sourceUrl": "https://www.bdspares.co.za/shop/alfa-romeo-brera-rear-bumper-05-11-w-pdc/",
    "name": "Alfa Romeo Brera Rear Bumper 05-11 (W/PDC)",
    "slug": "alfa-romeo-brera-rear-bumper-05-11-w-pdc",
    "sku": "",
    "priceZar": null,
    "inStock": true,
    "description": "Alfa Romeo Brera Rear Bumper 2005-2011 (With PDC)",
    "dimensions": null,
    "oemPartNumber": null,
    "alternatePartNumbers": [],
    "woocommerceCategory": "",
    "woocommerceBrandLabel": null,
    "imageUrls": [
      "https://www.bdspares.co.za/wp-content/uploads/2026/03/BD20404_69a68ed88fa87-scaled.jpeg"
    ],
    "lineJob": {
      "brandSlug": "alfa-romeo",
      "lineSlug": "feed",
      "path": "alfa-romeo/feed",
      "listingUrl": "https://www.bdspares.co.za/brands/alfa-romeo/feed/",
      "lineTitle": "Feed"
    }
  },
  {
    "sourceUrl": "https://www.bdspares.co.za/shop/alfa-romeo-159-rear-bumper-05-w-o-pdc/",
    "name": "Alfa Romeo 159 Rear Bumper 05- (W/O PDC)",
    "slug": "alfa-romeo-159-rear-bumper-05-w-o-pdc",
    "sku": "",
    "priceZar": null,
    "inStock": true,
    "description": "Alfa Romeo 159 Rear Bumper 2005- (Without PDC)",
    "dimensions": null,
    "oemPartNumber": null,
    "alternatePartNumbers": [],
    "woocommerceCategory": "",
    "woocommerceBrandLabel": null,
    "imageUrls": [
      "https://www.bdspares.co.za/wp-content/uploads/2026/03/BD20405_69a68edabad88-scaled.jpeg"
    ],
    "lineJob": {
      "brandSlug": "alfa-romeo",
      "lineSlug": "feed",
      "path": "alfa-romeo/feed",
      "listingUrl": "https://www.bdspares.co.za/brands/alfa-romeo/feed/",
      "lineTitle": "Feed"
    }
  }
]