[
  {
    "sourceUrl": "https://www.bdspares.co.za/shop/mercedes-benz-w124-radiator-94-95-auto-2-0l/",
    "name": "Mercedes-Benz W124 Radiator 94-95 (Auto / 2.0L)",
    "slug": "mercedes-benz-w124-radiator-94-95-auto-2-0l",
    "sku": "",
    "priceZar": null,
    "inStock": true,
    "description": "Mercedes-Benz W124 Radiator 1994-1995 (Automatic / 2.0L)",
    "dimensions": null,
    "oemPartNumber": null,
    "alternatePartNumbers": [],
    "woocommerceCategory": "",
    "woocommerceBrandLabel": null,
    "imageUrls": [],
    "lineJob": {
      "brandSlug": "mercedes-benz",
      "lineSlug": "feed",
      "path": "mercedes-benz/feed",
      "listingUrl": "https://www.bdspares.co.za/brands/mercedes-benz/feed/",
      "lineTitle": "Feed"
    }
  },
  {
    "sourceUrl": "https://www.bdspares.co.za/shop/mercedes-benz-w124-fan-blade-84/",
    "name": "Mercedes-Benz W124 Fan Blade 84-",
    "slug": "mercedes-benz-w124-fan-blade-84",
    "sku": "",
    "priceZar": null,
    "inStock": true,
    "description": "Mercedes-Benz W124 Fan Blade 1984-",
    "dimensions": null,
    "oemPartNumber": null,
    "alternatePartNumbers": [],
    "woocommerceCategory": "",
    "woocommerceBrandLabel": null,
    "imageUrls": [],
    "lineJob": {
      "brandSlug": "mercedes-benz",
      "lineSlug": "feed",
      "path": "mercedes-benz/feed",
      "listingUrl": "https://www.bdspares.co.za/brands/mercedes-benz/feed/",
      "lineTitle": "Feed"
    }
  },
  {
    "sourceUrl": "https://www.bdspares.co.za/shop/mercedes-benz-a-class-w169-main-grill-08-13-chrome-silver/",
    "name": "Mercedes Benz A-Class W169 Main Grill 08-13 (Chrome/Silver)",
    "slug": "mercedes-benz-a-class-w169-main-grill-08-13-chrome-silver",
    "sku": "",
    "priceZar": null,
    "inStock": true,
    "description": "Mercedes Benz A-Class W169 Main Grill 2008-2013 (Chrome/Silver)",
    "dimensions": null,
    "oemPartNumber": null,
    "alternatePartNumbers": [],
    "woocommerceCategory": "",
    "woocommerceBrandLabel": null,
    "imageUrls": [],
    "lineJob": {
      "brandSlug": "mercedes-benz",
      "lineSlug": "feed",
      "path": "mercedes-benz/feed",
      "listingUrl": "https://www.bdspares.co.za/brands/mercedes-benz/feed/",
      "lineTitle": "Feed"
    }
  },
  {
    "sourceUrl": "https://www.bdspares.co.za/shop/mercedes-benz-w202-radiator-93-c63-amg/",
    "name": "Mercedes-Benz W202 Radiator 93- (C63 AMG)",
    "slug": "mercedes-benz-w202-radiator-93-c63-amg",
    "sku": "",
    "priceZar": null,
    "inStock": true,
    "description": "Mercedes-Benz W202 Radiator 1993- (C63 AMG)",
    "dimensions": null,
    "oemPartNumber": null,
    "alternatePartNumbers": [],
    "woocommerceCategory": "",
    "woocommerceBrandLabel": null,
    "imageUrls": [],
    "lineJob": {
      "brandSlug": "mercedes-benz",
      "lineSlug": "feed",
      "path": "mercedes-benz/feed",
      "listingUrl": "https://www.bdspares.co.za/brands/mercedes-benz/feed/",
      "lineTitle": "Feed"
    }
  },
  {
    "sourceUrl": "https://www.bdspares.co.za/shop/mercedes-benz-w204-f-l-11-14-sport-front-bumper-plain/",
    "name": "Mercedes-Benz W204 F/L 11-14 Sport Front Bumper (Plain)",
    "slug": "mercedes-benz-w204-f-l-11-14-sport-front-bumper-plain",
    "sku": "",
    "priceZar": null,
    "inStock": true,
    "description": "Mercedes-Benz W204 F/L 2011-2014 Sport Front Bumper (Plain)",
    "dimensions": null,
    "oemPartNumber": null,
    "alternatePartNumbers": [],
    "woocommerceCategory": "",
    "woocommerceBrandLabel": null,
    "imageUrls": [],
    "lineJob": {
      "brandSlug": "mercedes-benz",
      "lineSlug": "feed",
      "path": "mercedes-benz/feed",
      "listingUrl": "https://www.bdspares.co.za/brands/mercedes-benz/feed/",
      "lineTitle": "Feed"
    }
  },
  {
    "sourceUrl": "https://www.bdspares.co.za/shop/mercedes-benz-w212-e-class-amg-facelift-rear-bumper-15-w-pdc/",
    "name": "Mercedes-Benz W212 E-Class AMG Facelift Rear Bumper 15- (W/PDC)",
    "slug": "mercedes-benz-w212-e-class-amg-facelift-rear-bumper-15-w-pdc",
    "sku": "",
    "priceZar": null,
    "inStock": true,
    "description": "Mercedes-Benz W212 E-Class AMG Facelift Rear Bumper 2015- (With PDC)",
    "dimensions": null,
    "oemPartNumber": null,
    "alternatePartNumbers": [],
    "woocommerceCategory": "",
    "woocommerceBrandLabel": null,
    "imageUrls": [],
    "lineJob": {
      "brandSlug": "mercedes-benz",
      "lineSlug": "feed",
      "path": "mercedes-benz/feed",
      "listingUrl": "https://www.bdspares.co.za/brands/mercedes-benz/feed/",
      "lineTitle": "Feed"
    }
  },
  {
    "sourceUrl": "https://www.bdspares.co.za/shop/mercedes-benz-w176-a-class-f-l-lhs-led-headlight-17/",
    "name": "Mercedes-Benz W176 A-Class F/L LHS LED Headlight 17-",
    "slug": "mercedes-benz-w176-a-class-f-l-lhs-led-headlight-17",
    "sku": "",
    "priceZar": null,
    "inStock": true,
    "description": "Mercedes-Benz W176 A-Class Facelift LHS LED Headlight 2017-",
    "dimensions": null,
    "oemPartNumber": null,
    "alternatePartNumbers": [],
    "woocommerceCategory": "",
    "woocommerceBrandLabel": null,
    "imageUrls": [],
    "lineJob": {
      "brandSlug": "mercedes-benz",
      "lineSlug": "feed",
      "path": "mercedes-benz/feed",
      "listingUrl": "https://www.bdspares.co.za/brands/mercedes-benz/feed/",
      "lineTitle": "Feed"
    }
  },
  {
    "sourceUrl": "https://www.bdspares.co.za/shop/u-mercedes-benz-w166-ml-lhs-xenon-headlight-12-15/",
    "name": "U – Mercedes Benz W166 ML LHS Xenon Headlight 12-15",
    "slug": "u-mercedes-benz-w166-ml-lhs-xenon-headlight-12-15",
    "sku": "",
    "priceZar": null,
    "inStock": true,
    "description": "Mercedes Benz W166 ML LHS Xenon Headlight 2012-2015",
    "dimensions": null,
    "oemPartNumber": null,
    "alternatePartNumbers": [],
    "woocommerceCategory": null,
    "woocommerceBrandLabel": null,
    "imageUrls": [],
    "lineJob": {
      "brandSlug": "mercedes-benz",
      "lineSlug": "feed",
      "path": "mercedes-benz/feed",
      "listingUrl": "https://www.bdspares.co.za/brands/mercedes-benz/feed/",
      "lineTitle": "Feed"
    }
  },
  {
    "sourceUrl": "https://www.bdspares.co.za/shop/mercedes-benz-w246-b-class-p-f-lhs-headlight-11/",
    "name": "Mercedes-Benz W246 B-Class P/F LHS Headlight 11-",
    "slug": "mercedes-benz-w246-b-class-p-f-lhs-headlight-11",
    "sku": "",
    "priceZar": null,
    "inStock": true,
    "description": "Mercedes-Benz W246 B-Class Preface LHS Headlight 2011-",
    "dimensions": null,
    "oemPartNumber": null,
    "alternatePartNumbers": [],
    "woocommerceCategory": "",
    "woocommerceBrandLabel": null,
    "imageUrls": [],
    "lineJob": {
      "brandSlug": "mercedes-benz",
      "lineSlug": "feed",
      "path": "mercedes-benz/feed",
      "listingUrl": "https://www.bdspares.co.za/brands/mercedes-benz/feed/",
      "lineTitle": "Feed"
    }
  },
  {
    "sourceUrl": "https://www.bdspares.co.za/shop/mercedes-benz-w246-b-class-p-f-rhs-headlight-11/",
    "name": "Mercedes-Benz W246 B-Class P/F RHS Headlight 11-",
    "slug": "mercedes-benz-w246-b-class-p-f-rhs-headlight-11",
    "sku": "",
    "priceZar": null,
    "inStock": true,
    "description": "Mercedes-Benz W246 B-Class Preface RHS Headlight 2011-",
    "dimensions": null,
    "oemPartNumber": null,
    "alternatePartNumbers": [],
    "woocommerceCategory": "",
    "woocommerceBrandLabel": null,
    "imageUrls": [],
    "lineJob": {
      "brandSlug": "mercedes-benz",
      "lineSlug": "feed",
      "path": "mercedes-benz/feed",
      "listingUrl": "https://www.bdspares.co.za/brands/mercedes-benz/feed/",
      "lineTitle": "Feed"
    }
  },
  {
    "sourceUrl": "https://www.bdspares.co.za/shop/imp-mercedes-benz-w117-w176-w156-w246-rad-water-bottle-12-18/",
    "name": "(IMP) Mercedes-Benz W117/W176/W156/W246 Rad Water Bottle 12-18",
    "slug": "imp-mercedes-benz-w117-w176-w156-w246-rad-water-bottle-12-18",
    "sku": "",
    "priceZar": null,
    "inStock": true,
    "description": "Mercedes-Benz W117/W176/W156/W246 Radiator Water Bottle 2012-2018",
    "dimensions": "",
    "oemPartNumber": null,
    "alternatePartNumbers": [],
    "woocommerceCategory": "",
    "woocommerceBrandLabel": null,
    "imageUrls": [
      "https://www.bdspares.co.za/wp-content/uploads/2023/07/POS_BD4833-scaled.jpg"
    ],
    "lineJob": {
      "brandSlug": "mercedes-benz",
      "lineSlug": "a-class",
      "path": "mercedes-benz/a-class",
      "listingUrl": "https://www.bdspares.co.za/brands/mercedes-benz/a-class/",
      "lineTitle": "A Class"
    }
  },
  {
    "sourceUrl": "https://www.bdspares.co.za/shop/imp-mercedes-benz-w117-w176-w246-lhs-chassis-support-leg-12-19/",
    "name": "(IMP) Mercedes-Benz W117/W176/W246/W156 LHS Chassis Support Leg 12-19",
    "slug": "imp-mercedes-benz-w117-w176-w246-lhs-chassis-support-leg-12-19",
    "sku": "",
    "priceZar": null,
    "inStock": true,
    "description": "Mercedes-Benz W117/W176/W246/W156 LHS Chassis Support Leg 2012-2019",
    "dimensions": "",
    "oemPartNumber": null,
    "alternatePartNumbers": [],
    "woocommerceCategory": null,
    "woocommerceBrandLabel": null,
    "imageUrls": [
      "https://www.bdspares.co.za/wp-content/uploads/2023/07/POS_BD4855-scaled.jpg"
    ],
    "lineJob": {
      "brandSlug": "mercedes-benz",
      "lineSlug": "a-class",
      "path": "mercedes-benz/a-class",
      "listingUrl": "https://www.bdspares.co.za/brands/mercedes-benz/a-class/",
      "lineTitle": "A Class"
    }
  },
  {
    "sourceUrl": "https://www.bdspares.co.za/shop/imp-mercedes-benz-w117-w176-w246-rhs-chassis-support-leg-12-19/",
    "name": "(IMP) Mercedes-Benz W117/W176/W246/W156 RHS Chassis Support Leg 12-19",
    "slug": "imp-mercedes-benz-w117-w176-w246-rhs-chassis-support-leg-12-19",
    "sku": "",
    "priceZar": null,
    "inStock": true,
    "description": "Mercedes-Benz W117/W176/W246/W156 RHS Chassis Support Leg 2012-2019",
    "dimensions": "",
    "oemPartNumber": null,
    "alternatePartNumbers": [],
    "woocommerceCategory": null,
    "woocommerceBrandLabel": null,
    "imageUrls": [
      "https://www.bdspares.co.za/wp-content/uploads/2023/07/POS_BD4856-scaled.jpg"
    ],
    "lineJob": {
      "brandSlug": "mercedes-benz",
      "lineSlug": "a-class",
      "path": "mercedes-benz/a-class",
      "listingUrl": "https://www.bdspares.co.za/brands/mercedes-benz/a-class/",
      "lineTitle": "A Class"
    }
  },
  {
    "sourceUrl": "https://www.bdspares.co.za/shop/imp-mercedes-benz-w176-a-class-bonnet-12-18-alum/",
    "name": "(IMP) Mercedes-Benz W176 A-Class Bonnet 12-18 (Alum)",
    "slug": "imp-mercedes-benz-w176-a-class-bonnet-12-18-alum",
    "sku": "",
    "priceZar": null,
    "inStock": true,
    "description": "Mercedes-Benz W176 A-Class Bonnet 2012-2018 (Aluminium)",
    "dimensions": "",
    "oemPartNumber": null,
    "alternatePartNumbers": [],
    "woocommerceCategory": "",
    "woocommerceBrandLabel": null,
    "imageUrls": [
      "https://www.bdspares.co.za/wp-content/uploads/2023/07/POS_BD6184.jpg"
    ],
    "lineJob": {
      "brandSlug": "mercedes-benz",
      "lineSlug": "a-class",
      "path": "mercedes-benz/a-class",
      "listingUrl": "https://www.bdspares.co.za/brands/mercedes-benz/a-class/",
      "lineTitle": "A Class"
    }
  },
  {
    "sourceUrl": "https://www.bdspares.co.za/shop/imp-mercedes-benz-w176-lhs-fender-13-18-w-o-hole/",
    "name": "(IMP) Mercedes-Benz W176 LHS Fender 13-18 (W/O Hole)",
    "slug": "imp-mercedes-benz-w176-lhs-fender-13-18-w-o-hole",
    "sku": "",
    "priceZar": null,
    "inStock": true,
    "description": "Mercedes-Benz W176 LHS Fender 2013-2018 (Without Marker Lamp Hole)",
    "dimensions": "",
    "oemPartNumber": null,
    "alternatePartNumbers": [],
    "woocommerceCategory": "",
    "woocommerceBrandLabel": null,
    "imageUrls": [
      "https://www.bdspares.co.za/wp-content/uploads/2023/07/POS_BD6197.jpg"
    ],
    "lineJob": {
      "brandSlug": "mercedes-benz",
      "lineSlug": "a-class",
      "path": "mercedes-benz/a-class",
      "listingUrl": "https://www.bdspares.co.za/brands/mercedes-benz/a-class/",
      "lineTitle": "A Class"
    }
  },
  {
    "sourceUrl": "https://www.bdspares.co.za/shop/mercedes-benz-w176-p-f-diamond-grill-imp/",
    "name": "(IMP) Mercedes-Benz W176 P/F Diamond Grill 14-16",
    "slug": "mercedes-benz-w176-p-f-diamond-grill-imp",
    "sku": "",
    "priceZar": null,
    "inStock": true,
    "description": "Mercedes-Benz W176 P/F Diamond Grill 2014-2016",
    "dimensions": "",
    "oemPartNumber": null,
    "alternatePartNumbers": [],
    "woocommerceCategory": "",
    "woocommerceBrandLabel": null,
    "imageUrls": [
      "https://www.bdspares.co.za/wp-content/uploads/2024/05/POS_BD479.jpg"
    ],
    "lineJob": {
      "brandSlug": "mercedes-benz",
      "lineSlug": "a-class",
      "path": "mercedes-benz/a-class",
      "listingUrl": "https://www.bdspares.co.za/brands/mercedes-benz/a-class/",
      "lineTitle": "A Class"
    }
  },
  {
    "sourceUrl": "https://www.bdspares.co.za/shop/imp-mercedes-benz-w177-amg-l-f-fender-liner-rear-21-w247/",
    "name": "(IMP) Mercedes-Benz W177 AMG L/F Fender Liner Rear 21- / W247",
    "slug": "imp-mercedes-benz-w177-amg-l-f-fender-liner-rear-21-w247",
    "sku": "",
    "priceZar": null,
    "inStock": true,
    "description": "Mercedes-Benz W177 AMG LHS Front Fender Liner Rear 2021- / W247",
    "dimensions": "",
    "oemPartNumber": null,
    "alternatePartNumbers": [],
    "woocommerceCategory": null,
    "woocommerceBrandLabel": null,
    "imageUrls": [
      "https://www.bdspares.co.za/wp-content/uploads/2024/05/POS_BD11401.jpg"
    ],
    "lineJob": {
      "brandSlug": "mercedes-benz",
      "lineSlug": "a-class",
      "path": "mercedes-benz/a-class",
      "listingUrl": "https://www.bdspares.co.za/brands/mercedes-benz/a-class/",
      "lineTitle": "A Class"
    }
  },
  {
    "sourceUrl": "https://www.bdspares.co.za/shop/imp-mercedes-benz-w177-amg-r-f-fender-liner-rear-21-w247/",
    "name": "(IMP) Mercedes-Benz W177 AMG R/F Fender Liner Rear 21- / W247",
    "slug": "imp-mercedes-benz-w177-amg-r-f-fender-liner-rear-21-w247",
    "sku": "",
    "priceZar": null,
    "inStock": true,
    "description": "Mercedes-Benz W177 AMG RHS Front Fender Liner Rear 2021- / W247",
    "dimensions": "",
    "oemPartNumber": null,
    "alternatePartNumbers": [],
    "woocommerceCategory": null,
    "woocommerceBrandLabel": null,
    "imageUrls": [
      "https://www.bdspares.co.za/wp-content/uploads/2024/05/POS_BD11402.jpg"
    ],
    "lineJob": {
      "brandSlug": "mercedes-benz",
      "lineSlug": "a-class",
      "path": "mercedes-benz/a-class",
      "listingUrl": "https://www.bdspares.co.za/brands/mercedes-benz/a-class/",
      "lineTitle": "A Class"
    }
  },
  {
    "sourceUrl": "https://www.bdspares.co.za/shop/imp-mercedes-benz-w177-l-f-fender-liner-front-18-w247/",
    "name": "(IMP) Mercedes-Benz W177 L/F Fender Liner Front 18- / W247",
    "slug": "imp-mercedes-benz-w177-l-f-fender-liner-front-18-w247",
    "sku": "",
    "priceZar": null,
    "inStock": true,
    "description": "Mercedes-Benz W177 LHS Front Fender Liner Front 2018- / W247",
    "dimensions": "",
    "oemPartNumber": null,
    "alternatePartNumbers": [],
    "woocommerceCategory": null,
    "woocommerceBrandLabel": null,
    "imageUrls": [
      "https://www.bdspares.co.za/wp-content/uploads/2023/07/POS_BD4685.jpg"
    ],
    "lineJob": {
      "brandSlug": "mercedes-benz",
      "lineSlug": "a-class",
      "path": "mercedes-benz/a-class",
      "listingUrl": "https://www.bdspares.co.za/brands/mercedes-benz/a-class/",
      "lineTitle": "A Class"
    }
  },
  {
    "sourceUrl": "https://www.bdspares.co.za/shop/imp-mercedes-benz-w177-l-f-fender-liner-rear-18-w247/",
    "name": "(IMP) Mercedes-Benz W177 L/F Fender Liner Rear 18- / W247",
    "slug": "imp-mercedes-benz-w177-l-f-fender-liner-rear-18-w247",
    "sku": "",
    "priceZar": null,
    "inStock": true,
    "description": "Mercedes-Benz W177 LHS Front Fender Liner Rear 2018- / W247",
    "dimensions": "",
    "oemPartNumber": null,
    "alternatePartNumbers": [],
    "woocommerceCategory": null,
    "woocommerceBrandLabel": null,
    "imageUrls": [
      "https://www.bdspares.co.za/wp-content/uploads/2023/07/POS_BD4687.jpg"
    ],
    "lineJob": {
      "brandSlug": "mercedes-benz",
      "lineSlug": "a-class",
      "path": "mercedes-benz/a-class",
      "listingUrl": "https://www.bdspares.co.za/brands/mercedes-benz/a-class/",
      "lineTitle": "A Class"
    }
  },
  {
    "sourceUrl": "https://www.bdspares.co.za/shop/imp-mercedes-benz-w177-r-f-fender-liner-front-18-w247/",
    "name": "(IMP) Mercedes-Benz W177 R/F Fender Liner Front 18- / W247",
    "slug": "imp-mercedes-benz-w177-r-f-fender-liner-front-18-w247",
    "sku": "",
    "priceZar": null,
    "inStock": true,
    "description": "Mercedes-Benz W177 RHS Front Fender Liner Front 2018- / W247",
    "dimensions": "",
    "oemPartNumber": null,
    "alternatePartNumbers": [],
    "woocommerceCategory": null,
    "woocommerceBrandLabel": null,
    "imageUrls": [
      "https://www.bdspares.co.za/wp-content/uploads/2023/07/POS_BD4686.jpg"
    ],
    "lineJob": {
      "brandSlug": "mercedes-benz",
      "lineSlug": "a-class",
      "path": "mercedes-benz/a-class",
      "listingUrl": "https://www.bdspares.co.za/brands/mercedes-benz/a-class/",
      "lineTitle": "A Class"
    }
  },
  {
    "sourceUrl": "https://www.bdspares.co.za/shop/imp-mercedes-benz-w177-r-f-fender-liner-rear-18-w247/",
    "name": "(IMP) Mercedes-Benz W177 R/F Fender Liner Rear 18- / W247",
    "slug": "imp-mercedes-benz-w177-r-f-fender-liner-rear-18-w247",
    "sku": "",
    "priceZar": null,
    "inStock": true,
    "description": "Mercedes-Benz W177 RHS Front Fender Liner Rear 2018- / W247",
    "dimensions": "",
    "oemPartNumber": null,
    "alternatePartNumbers": [],
    "woocommerceCategory": null,
    "woocommerceBrandLabel": null,
    "imageUrls": [
      "https://www.bdspares.co.za/wp-content/uploads/2023/07/POS_BD4688.jpg"
    ],
    "lineJob": {
      "brandSlug": "mercedes-benz",
      "lineSlug": "a-class",
      "path": "mercedes-benz/a-class",
      "listingUrl": "https://www.bdspares.co.za/brands/mercedes-benz/a-class/",
      "lineTitle": "A Class"
    }
  },
  {
    "sourceUrl": "https://www.bdspares.co.za/shop/mercedes-benz-a45-w176-cla45-w117-gla45-w156-amg-radiator-13/",
    "name": "Mercedes Benz A45 W176 / CLA45 W117 / GLA45 W156 AMG Radiator 13-",
    "slug": "mercedes-benz-a45-w176-cla45-w117-gla45-w156-amg-radiator-13",
    "sku": "",
    "priceZar": null,
    "inStock": true,
    "description": "Mercedes Benz A45 W176 / CLA45 W117 / GLA45 W156 AMG Radiator 2013-",
    "dimensions": null,
    "oemPartNumber": null,
    "alternatePartNumbers": [],
    "woocommerceCategory": "",
    "woocommerceBrandLabel": null,
    "imageUrls": [
      "https://www.bdspares.co.za/wp-content/uploads/2025/08/BD17543_68921e9d0768e.jpeg"
    ],
    "lineJob": {
      "brandSlug": "mercedes-benz",
      "lineSlug": "a-class",
      "path": "mercedes-benz/a-class",
      "listingUrl": "https://www.bdspares.co.za/brands/mercedes-benz/a-class/",
      "lineTitle": "A Class"
    }
  },
  {
    "sourceUrl": "https://www.bdspares.co.za/shop/mercedes-benz-w177-amg-front-bumper-with-pdc-2018/",
    "name": "Mercedes Benz W177 AMG Front Bumper (With PDC) 2018-",
    "slug": "mercedes-benz-w177-amg-front-bumper-with-pdc-2018",
    "sku": "",
    "priceZar": null,
    "inStock": true,
    "description": "Mercedes Benz W177 AMG Front Bumper (With PDC) 2018-",
    "dimensions": null,
    "oemPartNumber": null,
    "alternatePartNumbers": [],
    "woocommerceCategory": null,
    "woocommerceBrandLabel": null,
    "imageUrls": [
      "https://www.bdspares.co.za/wp-content/uploads/2025/08/BD3927-1_6892149a41016.jpeg"
    ],
    "lineJob": {
      "brandSlug": "mercedes-benz",
      "lineSlug": "a-class",
      "path": "mercedes-benz/a-class",
      "listingUrl": "https://www.bdspares.co.za/brands/mercedes-benz/a-class/",
      "lineTitle": "A Class"
    }
  },
  {
    "sourceUrl": "https://www.bdspares.co.za/shop/mercedes-benz-w168-lhs-taillight-02-smoked/",
    "name": "Mercedes-Benz W168 LHS Taillight 02- (Smoked)",
    "slug": "mercedes-benz-w168-lhs-taillight-02-smoked",
    "sku": "",
    "priceZar": null,
    "inStock": true,
    "description": "Mercedes-Benz W168 LHS Taillight 02- (Smoked)",
    "dimensions": "",
    "oemPartNumber": null,
    "alternatePartNumbers": [],
    "woocommerceCategory": "",
    "woocommerceBrandLabel": null,
    "imageUrls": [
      "https://www.bdspares.co.za/wp-content/uploads/2024/02/POS_BD800.jpg"
    ],
    "lineJob": {
      "brandSlug": "mercedes-benz",
      "lineSlug": "a-class",
      "path": "mercedes-benz/a-class",
      "listingUrl": "https://www.bdspares.co.za/brands/mercedes-benz/a-class/",
      "lineTitle": "A Class"
    }
  },
  {
    "sourceUrl": "https://www.bdspares.co.za/shop/mercedes-benz-w169-a-class-rhs-headlight-09-12/",
    "name": "Mercedes-Benz W169 A-Class RHS Headlight 09-12",
    "slug": "mercedes-benz-w169-a-class-rhs-headlight-09-12",
    "sku": "",
    "priceZar": null,
    "inStock": true,
    "description": "Mercedes-Benz W169 A-Class RHS Headlight 2009-2012",
    "dimensions": "",
    "oemPartNumber": null,
    "alternatePartNumbers": [],
    "woocommerceCategory": "",
    "woocommerceBrandLabel": null,
    "imageUrls": [
      "https://www.bdspares.co.za/wp-content/uploads/2025/02/POS_BD4164.jpg"
    ],
    "lineJob": {
      "brandSlug": "mercedes-benz",
      "lineSlug": "a-class",
      "path": "mercedes-benz/a-class",
      "listingUrl": "https://www.bdspares.co.za/brands/mercedes-benz/a-class/",
      "lineTitle": "A Class"
    }
  },
  {
    "sourceUrl": "https://www.bdspares.co.za/shop/mercedes-benz-w169-lhs-headlight-04-08/",
    "name": "Mercedes-Benz W169 LHS Headlight 04-08",
    "slug": "mercedes-benz-w169-lhs-headlight-04-08",
    "sku": "",
    "priceZar": null,
    "inStock": true,
    "description": "Mercedes-Benz W169 Left Hand Side Headlight 2004-2008",
    "dimensions": "",
    "oemPartNumber": null,
    "alternatePartNumbers": [],
    "woocommerceCategory": "",
    "woocommerceBrandLabel": null,
    "imageUrls": [
      "https://www.bdspares.co.za/wp-content/uploads/2023/10/POS_BD8370.jpg"
    ],
    "lineJob": {
      "brandSlug": "mercedes-benz",
      "lineSlug": "a-class",
      "path": "mercedes-benz/a-class",
      "listingUrl": "https://www.bdspares.co.za/brands/mercedes-benz/a-class/",
      "lineTitle": "A Class"
    }
  },
  {
    "sourceUrl": "https://www.bdspares.co.za/shop/mercedes-benz-w169-lhs-prj-headlight-05-08-depo/",
    "name": "Mercedes-Benz W169 LHS Prj Headlight 04-08",
    "slug": "mercedes-benz-w169-lhs-prj-headlight-05-08-depo",
    "sku": "",
    "priceZar": null,
    "inStock": true,
    "description": "Mercedes-Benz W169 LHS Projector Headlight 2004-2008",
    "dimensions": "",
    "oemPartNumber": null,
    "alternatePartNumbers": [],
    "woocommerceCategory": "",
    "woocommerceBrandLabel": null,
    "imageUrls": [
      "https://www.bdspares.co.za/wp-content/uploads/2024/07/POS_BD11931.jpg"
    ],
    "lineJob": {
      "brandSlug": "mercedes-benz",
      "lineSlug": "a-class",
      "path": "mercedes-benz/a-class",
      "listingUrl": "https://www.bdspares.co.za/brands/mercedes-benz/a-class/",
      "lineTitle": "A Class"
    }
  },
  {
    "sourceUrl": "https://www.bdspares.co.za/shop/mercedes-benz-w169-rear-bumper-04-w-mldngprimed/",
    "name": "Mercedes-Benz W169 Rear Bumper 04- (W/Mldng,Primed)",
    "slug": "mercedes-benz-w169-rear-bumper-04-w-mldngprimed",
    "sku": "",
    "priceZar": null,
    "inStock": true,
    "description": "Mercedes-Benz W169 Rear Bumper 2004- (With Moulding Hole,Primed)",
    "dimensions": "",
    "oemPartNumber": null,
    "alternatePartNumbers": [],
    "woocommerceCategory": null,
    "woocommerceBrandLabel": null,
    "imageUrls": [
      "https://www.bdspares.co.za/wp-content/uploads/2025/02/POS_BD13234.jpeg"
    ],
    "lineJob": {
      "brandSlug": "mercedes-benz",
      "lineSlug": "a-class",
      "path": "mercedes-benz/a-class",
      "listingUrl": "https://www.bdspares.co.za/brands/mercedes-benz/a-class/",
      "lineTitle": "A Class"
    }
  },
  {
    "sourceUrl": "https://www.bdspares.co.za/shop/mercedes-benz-w176-condenser-13-18-180-250/",
    "name": "Mercedes-Benz W176 / W117 / W156 Condenser 2013-2018 (A45 / CLA45 / GLA45 AMG)",
    "slug": "mercedes-benz-w176-condenser-13-18-180-250",
    "sku": "",
    "priceZar": null,
    "inStock": true,
    "description": "Mercedes-Benz W176 / W117 / W156 Condenser 2013-2018 (A45 / CLA45 / GLA45 AMG)",
    "dimensions": "",
    "oemPartNumber": null,
    "alternatePartNumbers": [],
    "woocommerceCategory": "",
    "woocommerceBrandLabel": null,
    "imageUrls": [
      "https://www.bdspares.co.za/wp-content/uploads/2024/05/POS_BD5793.jpg"
    ],
    "lineJob": {
      "brandSlug": "mercedes-benz",
      "lineSlug": "a-class",
      "path": "mercedes-benz/a-class",
      "listingUrl": "https://www.bdspares.co.za/brands/mercedes-benz/a-class/",
      "lineTitle": "A Class"
    }
  },
  {
    "sourceUrl": "https://www.bdspares.co.za/shop/mercedes-benz-w176-a-class-f-l-rhs-led-headlight-17/",
    "name": "Mercedes-Benz W176 A-Class F/L RHS LED Headlight 17-",
    "slug": "mercedes-benz-w176-a-class-f-l-rhs-led-headlight-17",
    "sku": "",
    "priceZar": null,
    "inStock": true,
    "description": "Mercedes-Benz W176 A-Class Facelift RHS LED Headlight 2017-",
    "dimensions": null,
    "oemPartNumber": null,
    "alternatePartNumbers": [],
    "woocommerceCategory": "",
    "woocommerceBrandLabel": null,
    "imageUrls": [],
    "lineJob": {
      "brandSlug": "mercedes-benz",
      "lineSlug": "a-class",
      "path": "mercedes-benz/a-class",
      "listingUrl": "https://www.bdspares.co.za/brands/mercedes-benz/a-class/",
      "lineTitle": "A Class"
    }
  },
  {
    "sourceUrl": "https://www.bdspares.co.za/shop/mercedes-benz-w176-fan-13-18-180-200/",
    "name": "Mercedes-Benz W176 Fan 13-18 (180/200)",
    "slug": "mercedes-benz-w176-fan-13-18-180-200",
    "sku": "",
    "priceZar": null,
    "inStock": true,
    "description": "Mercedes-Benz W176 Fan 2013-2018 (180/200)",
    "dimensions": "",
    "oemPartNumber": null,
    "alternatePartNumbers": [],
    "woocommerceCategory": "",
    "woocommerceBrandLabel": null,
    "imageUrls": [
      "https://www.bdspares.co.za/wp-content/uploads/2023/07/POS_bd5901.jpg"
    ],
    "lineJob": {
      "brandSlug": "mercedes-benz",
      "lineSlug": "a-class",
      "path": "mercedes-benz/a-class",
      "listingUrl": "https://www.bdspares.co.za/brands/mercedes-benz/a-class/",
      "lineTitle": "A Class"
    }
  },
  {
    "sourceUrl": "https://www.bdspares.co.za/shop/mercedes-benz-w176-module/",
    "name": "Mercedes-Benz W176 Module",
    "slug": "mercedes-benz-w176-module",
    "sku": "",
    "priceZar": null,
    "inStock": true,
    "description": "Mercedes-Benz W176 Module",
    "dimensions": "",
    "oemPartNumber": null,
    "alternatePartNumbers": [],
    "woocommerceCategory": "",
    "woocommerceBrandLabel": null,
    "imageUrls": [
      "https://www.bdspares.co.za/wp-content/uploads/2024/04/POS_BD455.jpg"
    ],
    "lineJob": {
      "brandSlug": "mercedes-benz",
      "lineSlug": "a-class",
      "path": "mercedes-benz/a-class",
      "listingUrl": "https://www.bdspares.co.za/brands/mercedes-benz/a-class/",
      "lineTitle": "A Class"
    }
  },
  {
    "sourceUrl": "https://www.bdspares.co.za/shop/mercedes-benz-w176-p-f-lhs-headlight-xenon-intelligent-15-a-class/",
    "name": "Mercedes-Benz W176 P/F LHS Headlight Xenon (Intelligent) 15- (A-Class)",
    "slug": "mercedes-benz-w176-p-f-lhs-headlight-xenon-intelligent-15-a-class",
    "sku": "",
    "priceZar": null,
    "inStock": true,
    "description": "Mercedes-Benz W176 P/F LHS Headlight Xenon (Intelligent) 2015- (A-Class)",
    "dimensions": "",
    "oemPartNumber": null,
    "alternatePartNumbers": [],
    "woocommerceCategory": "",
    "woocommerceBrandLabel": null,
    "imageUrls": [
      "https://www.bdspares.co.za/wp-content/uploads/2024/03/POS_BD3536.jpg"
    ],
    "lineJob": {
      "brandSlug": "mercedes-benz",
      "lineSlug": "a-class",
      "path": "mercedes-benz/a-class",
      "listingUrl": "https://www.bdspares.co.za/brands/mercedes-benz/a-class/",
      "lineTitle": "A Class"
    }
  },
  {
    "sourceUrl": "https://www.bdspares.co.za/shop/mercedes-benz-w176-p-f-rhs-headlight-xenon-intelligent-15-a-class/",
    "name": "Mercedes-Benz W176 P/F RHS Headlight Xenon (Intelligent) 15- (A-Class)",
    "slug": "mercedes-benz-w176-p-f-rhs-headlight-xenon-intelligent-15-a-class",
    "sku": "",
    "priceZar": null,
    "inStock": true,
    "description": "Mercedes-Benz W176 P/F RHS Headlight Xenon (Intelligent) 2015- (A-Class)",
    "dimensions": "",
    "oemPartNumber": null,
    "alternatePartNumbers": [],
    "woocommerceCategory": "",
    "woocommerceBrandLabel": null,
    "imageUrls": [
      "https://www.bdspares.co.za/wp-content/uploads/2024/03/POS_BD3537.jpg"
    ],
    "lineJob": {
      "brandSlug": "mercedes-benz",
      "lineSlug": "a-class",
      "path": "mercedes-benz/a-class",
      "listingUrl": "https://www.bdspares.co.za/brands/mercedes-benz/a-class/",
      "lineTitle": "A Class"
    }
  },
  {
    "sourceUrl": "https://www.bdspares.co.za/shop/mercedes-benz-w156-w176-w117-module/",
    "name": "Mercedes-Benz W176/W117 LED Module",
    "slug": "mercedes-benz-w156-w176-w117-module",
    "sku": "",
    "priceZar": null,
    "inStock": true,
    "description": "Mercedes-Benz W176/W117 LED Module",
    "dimensions": "",
    "oemPartNumber": null,
    "alternatePartNumbers": [],
    "woocommerceCategory": "",
    "woocommerceBrandLabel": null,
    "imageUrls": [
      "https://www.bdspares.co.za/wp-content/uploads/2024/04/POS_BD461.jpg"
    ],
    "lineJob": {
      "brandSlug": "mercedes-benz",
      "lineSlug": "a-class",
      "path": "mercedes-benz/a-class",
      "listingUrl": "https://www.bdspares.co.za/brands/mercedes-benz/a-class/",
      "lineTitle": "A Class"
    }
  },
  {
    "sourceUrl": "https://www.bdspares.co.za/shop/mercedes-benz-w176-w246-w117-radiator-12/",
    "name": "Mercedes-Benz W176/W246/W117 Radiator 12-",
    "slug": "mercedes-benz-w176-w246-w117-radiator-12",
    "sku": "",
    "priceZar": null,
    "inStock": true,
    "description": "Mercedes-Benz W176/W246/W117 Radiator 2012-",
    "dimensions": null,
    "oemPartNumber": null,
    "alternatePartNumbers": [],
    "woocommerceCategory": "",
    "woocommerceBrandLabel": null,
    "imageUrls": [
      "https://www.bdspares.co.za/wp-content/uploads/2025/08/BD14299_689276689bf84.jpeg"
    ],
    "lineJob": {
      "brandSlug": "mercedes-benz",
      "lineSlug": "a-class",
      "path": "mercedes-benz/a-class",
      "listingUrl": "https://www.bdspares.co.za/brands/mercedes-benz/a-class/",
      "lineTitle": "A Class"
    }
  },
  {
    "sourceUrl": "https://www.bdspares.co.za/shop/mercedes-benz-w177-lhs-multi-beam-headlight/",
    "name": "Mercedes-Benz W177 LHS Multi-Beam Headlight",
    "slug": "mercedes-benz-w177-lhs-multi-beam-headlight",
    "sku": "",
    "priceZar": null,
    "inStock": true,
    "description": "Mercedes-Benz W177 LHS Multi-Beam Headlight",
    "dimensions": "",
    "oemPartNumber": null,
    "alternatePartNumbers": [],
    "woocommerceCategory": "",
    "woocommerceBrandLabel": null,
    "imageUrls": [
      "https://www.bdspares.co.za/wp-content/uploads/2024/05/POS_BD4619202.jpeg"
    ],
    "lineJob": {
      "brandSlug": "mercedes-benz",
      "lineSlug": "a-class",
      "path": "mercedes-benz/a-class",
      "listingUrl": "https://www.bdspares.co.za/brands/mercedes-benz/a-class/",
      "lineTitle": "A Class"
    }
  },
  {
    "sourceUrl": "https://www.bdspares.co.za/shop/mercedes-benz-w177-lhs-single-xenon-headlight-19-22-oem/",
    "name": "Mercedes-Benz W177 LHS Single Xenon Headlight 19-22 (OEM)",
    "slug": "mercedes-benz-w177-lhs-single-xenon-headlight-19-22-oem",
    "sku": "",
    "priceZar": null,
    "inStock": true,
    "description": "Mercedes-Benz W177 LHS Single Xenon Headlight 2019-2022",
    "dimensions": null,
    "oemPartNumber": null,
    "alternatePartNumbers": [],
    "woocommerceCategory": "",
    "woocommerceBrandLabel": null,
    "imageUrls": [
      "https://www.bdspares.co.za/wp-content/uploads/2025/08/BD17185_689233384a731.jpeg"
    ],
    "lineJob": {
      "brandSlug": "mercedes-benz",
      "lineSlug": "a-class",
      "path": "mercedes-benz/a-class",
      "listingUrl": "https://www.bdspares.co.za/brands/mercedes-benz/a-class/",
      "lineTitle": "A Class"
    }
  },
  {
    "sourceUrl": "https://www.bdspares.co.za/shop/mercedes-benz-w177-rhs-multi-beam-xenon-headlight-19/",
    "name": "Mercedes-Benz W177 RHS Multi Beam Xenon Headlight 19-",
    "slug": "mercedes-benz-w177-rhs-multi-beam-xenon-headlight-19",
    "sku": "",
    "priceZar": null,
    "inStock": true,
    "description": "Mercedes-Benz W177 RHS Multi Beam Xenon Headlight 2019-",
    "dimensions": "",
    "oemPartNumber": null,
    "alternatePartNumbers": [],
    "woocommerceCategory": "",
    "woocommerceBrandLabel": null,
    "imageUrls": [
      "https://www.bdspares.co.za/wp-content/uploads/2023/07/POS_BD4613.jpeg"
    ],
    "lineJob": {
      "brandSlug": "mercedes-benz",
      "lineSlug": "a-class",
      "path": "mercedes-benz/a-class",
      "listingUrl": "https://www.bdspares.co.za/brands/mercedes-benz/a-class/",
      "lineTitle": "A Class"
    }
  },
  {
    "sourceUrl": "https://www.bdspares.co.za/shop/mercedes-benz-w177-rhs-single-xenon-headlight-19-22-oem/",
    "name": "Mercedes-Benz W177 RHS Single Xenon Headlight 19-22 (OEM)",
    "slug": "mercedes-benz-w177-rhs-single-xenon-headlight-19-22-oem",
    "sku": "",
    "priceZar": null,
    "inStock": true,
    "description": "Mercedes-Benz W177 RHS Single Xenon Headlight 2019-2022",
    "dimensions": null,
    "oemPartNumber": null,
    "alternatePartNumbers": [],
    "woocommerceCategory": "",
    "woocommerceBrandLabel": null,
    "imageUrls": [
      "https://www.bdspares.co.za/wp-content/uploads/2025/08/BD17186_689233ce8b548.jpeg"
    ],
    "lineJob": {
      "brandSlug": "mercedes-benz",
      "lineSlug": "a-class",
      "path": "mercedes-benz/a-class",
      "listingUrl": "https://www.bdspares.co.za/brands/mercedes-benz/a-class/",
      "lineTitle": "A Class"
    }
  },
  {
    "sourceUrl": "https://www.bdspares.co.za/shop/mercedes-benz-w205-l-f-bumper-slide-15/",
    "name": "Mercedes-Benz W205 L/F Bumper Slide 15-",
    "slug": "mercedes-benz-w205-l-f-bumper-slide-15",
    "sku": "",
    "priceZar": null,
    "inStock": true,
    "description": "Mercedes-Benz W205 L/F Bumper Slide 2015-",
    "dimensions": null,
    "oemPartNumber": null,
    "alternatePartNumbers": [],
    "woocommerceCategory": "",
    "woocommerceBrandLabel": null,
    "imageUrls": [],
    "lineJob": {
      "brandSlug": "mercedes-benz",
      "lineSlug": "a-class",
      "path": "mercedes-benz/a-class",
      "listingUrl": "https://www.bdspares.co.za/brands/mercedes-benz/a-class/",
      "lineTitle": "A Class"
    }
  },
  {
    "sourceUrl": "https://www.bdspares.co.za/shop/u-mercedes-benz-a-class-w169-07-right-side-taillight/",
    "name": "U – Mercedes-Benz A-Class W169 RHS Taillight 05-08 (SMKD)",
    "slug": "u-mercedes-benz-a-class-w169-07-right-side-taillight",
    "sku": "",
    "priceZar": null,
    "inStock": true,
    "description": "Mercedes-Benz A-Class W169 RHS Taillight 2005-2008 (Smoked)",
    "dimensions": "",
    "oemPartNumber": null,
    "alternatePartNumbers": [],
    "woocommerceCategory": "",
    "woocommerceBrandLabel": null,
    "imageUrls": [
      "https://www.bdspares.co.za/wp-content/uploads/2025/06/POS_BDU17.jpg"
    ],
    "lineJob": {
      "brandSlug": "mercedes-benz",
      "lineSlug": "a-class",
      "path": "mercedes-benz/a-class",
      "listingUrl": "https://www.bdspares.co.za/brands/mercedes-benz/a-class/",
      "lineTitle": "A Class"
    }
  },
  {
    "sourceUrl": "https://www.bdspares.co.za/shop/u-mercedes-benz-w177-a-class-lhs-xenon-headlight-19/",
    "name": "U – Mercedes-Benz A177 LHS Multi-Beam LED Headlight 18-",
    "slug": "u-mercedes-benz-w177-a-class-lhs-xenon-headlight-19",
    "sku": "",
    "priceZar": null,
    "inStock": true,
    "description": "Mercedes-Benz A177 LHS Multi-Beam LED Headlight 2018-",
    "dimensions": "",
    "oemPartNumber": null,
    "alternatePartNumbers": [],
    "woocommerceCategory": "",
    "woocommerceBrandLabel": null,
    "imageUrls": [
      "https://www.bdspares.co.za/wp-content/uploads/2025/07/POS_Copyofbd15285(59).jpg"
    ],
    "lineJob": {
      "brandSlug": "mercedes-benz",
      "lineSlug": "a-class",
      "path": "mercedes-benz/a-class",
      "listingUrl": "https://www.bdspares.co.za/brands/mercedes-benz/a-class/",
      "lineTitle": "A Class"
    }
  },
  {
    "sourceUrl": "https://www.bdspares.co.za/shop/u-mercedes-benz-a-class-w169-2008-2012-left-hand-side-taillight/",
    "name": "U – Mercedes-Benz ML W164 RHS LED Taillight 02-11",
    "slug": "u-mercedes-benz-a-class-w169-2008-2012-left-hand-side-taillight",
    "sku": "",
    "priceZar": null,
    "inStock": true,
    "description": "Mercedes-Benz ML W164 RHS LED Taillight 2002-2011",
    "dimensions": "",
    "oemPartNumber": null,
    "alternatePartNumbers": [],
    "woocommerceCategory": "",
    "woocommerceBrandLabel": null,
    "imageUrls": [
      "https://www.bdspares.co.za/wp-content/uploads/2025/06/POS_BDU88.jpg"
    ],
    "lineJob": {
      "brandSlug": "mercedes-benz",
      "lineSlug": "a-class",
      "path": "mercedes-benz/a-class",
      "listingUrl": "https://www.bdspares.co.za/brands/mercedes-benz/a-class/",
      "lineTitle": "A Class"
    }
  },
  {
    "sourceUrl": "https://www.bdspares.co.za/shop/u-mercedes-benz-a-class-w177-led-18-21-right-side-outer-taillight/",
    "name": "U – Mercedes-Benz SL55 AMG P/F LHS Taillight 08-",
    "slug": "u-mercedes-benz-a-class-w177-led-18-21-right-side-outer-taillight",
    "sku": "",
    "priceZar": null,
    "inStock": true,
    "description": "Mercedes-Benz SL55 AMG Preface LHS Taillight 2008-",
    "dimensions": "",
    "oemPartNumber": null,
    "alternatePartNumbers": [],
    "woocommerceCategory": "",
    "woocommerceBrandLabel": null,
    "imageUrls": [
      "https://www.bdspares.co.za/wp-content/uploads/2025/06/POS_BDU96.jpg"
    ],
    "lineJob": {
      "brandSlug": "mercedes-benz",
      "lineSlug": "a-class",
      "path": "mercedes-benz/a-class",
      "listingUrl": "https://www.bdspares.co.za/brands/mercedes-benz/a-class/",
      "lineTitle": "A Class"
    }
  },
  {
    "sourceUrl": "https://www.bdspares.co.za/shop/u-mercedes-benz-w169-a-class-2008-2012-non-xenon-left-hand-side-headlight/",
    "name": "U – Mercedes-Benz W168 LHS Headlight 04-",
    "slug": "u-mercedes-benz-w169-a-class-2008-2012-non-xenon-left-hand-side-headlight",
    "sku": "",
    "priceZar": null,
    "inStock": true,
    "description": "Mercedes-Benz W168 LHS Headlight 2004-",
    "dimensions": "",
    "oemPartNumber": null,
    "alternatePartNumbers": [],
    "woocommerceCategory": "",
    "woocommerceBrandLabel": null,
    "imageUrls": [
      "https://www.bdspares.co.za/wp-content/uploads/2025/07/POS_Copyofbd15285(100).jpg"
    ],
    "lineJob": {
      "brandSlug": "mercedes-benz",
      "lineSlug": "a-class",
      "path": "mercedes-benz/a-class",
      "listingUrl": "https://www.bdspares.co.za/brands/mercedes-benz/a-class/",
      "lineTitle": "A Class"
    }
  },
  {
    "sourceUrl": "https://www.bdspares.co.za/shop/u-mercedes-benz-a-class-w169-07-left-side-taillight-1/",
    "name": "U – Mercedes-Benz W169 LHS Taillight 05-08 (STD)",
    "slug": "u-mercedes-benz-a-class-w169-07-left-side-taillight-1",
    "sku": "",
    "priceZar": null,
    "inStock": true,
    "description": "Mercedes-Benz W169 LHS Taillight 2005-2008 (Standard)",
    "dimensions": "",
    "oemPartNumber": null,
    "alternatePartNumbers": [],
    "woocommerceCategory": "",
    "woocommerceBrandLabel": null,
    "imageUrls": [
      "https://www.bdspares.co.za/wp-content/uploads/2025/06/POS_BDU15.jpg"
    ],
    "lineJob": {
      "brandSlug": "mercedes-benz",
      "lineSlug": "a-class",
      "path": "mercedes-benz/a-class",
      "listingUrl": "https://www.bdspares.co.za/brands/mercedes-benz/a-class/",
      "lineTitle": "A Class"
    }
  },
  {
    "sourceUrl": "https://www.bdspares.co.za/shop/u-mercedes-benz-a-class-w169-07-left-side-taillight/",
    "name": "U – Mercedes-Benz W169 RHS Taillight 05-08 (STD)",
    "slug": "u-mercedes-benz-a-class-w169-07-left-side-taillight",
    "sku": "",
    "priceZar": null,
    "inStock": true,
    "description": "Mercedes-Benz W169 RHS Taillight 2005-2008 (Standard)",
    "dimensions": "",
    "oemPartNumber": null,
    "alternatePartNumbers": [],
    "woocommerceCategory": "",
    "woocommerceBrandLabel": null,
    "imageUrls": [
      "https://www.bdspares.co.za/wp-content/uploads/2024/07/POS_1797.jpeg"
    ],
    "lineJob": {
      "brandSlug": "mercedes-benz",
      "lineSlug": "a-class",
      "path": "mercedes-benz/a-class",
      "listingUrl": "https://www.bdspares.co.za/brands/mercedes-benz/a-class/",
      "lineTitle": "A Class"
    }
  },
  {
    "sourceUrl": "https://www.bdspares.co.za/shop/u-mercedes-benz-w176-a-class-rhs-intelligent-xenon-headlight-12/",
    "name": "U – Mercedes-Benz W176 F/L RHS Xenon Headlight 17-",
    "slug": "u-mercedes-benz-w176-a-class-rhs-intelligent-xenon-headlight-12",
    "sku": "",
    "priceZar": null,
    "inStock": true,
    "description": "Mercedes-Benz W176 Facelift RHS Xenon Headlight 2017-",
    "dimensions": "",
    "oemPartNumber": null,
    "alternatePartNumbers": [],
    "woocommerceCategory": "",
    "woocommerceBrandLabel": null,
    "imageUrls": [
      "https://www.bdspares.co.za/wp-content/uploads/2025/07/POS_Copyofbd15285(84).jpg"
    ],
    "lineJob": {
      "brandSlug": "mercedes-benz",
      "lineSlug": "a-class",
      "path": "mercedes-benz/a-class",
      "listingUrl": "https://www.bdspares.co.za/brands/mercedes-benz/a-class/",
      "lineTitle": "A Class"
    }
  }
]